{"type": "FeatureCollection","features":[{"type": "Feature","geometry": {"type": "Point","coordinates": [-123.139911,45.436118]},"properties": {"inspections": [{"restId":"34006268","inspectId":"54007495","inspectType":"SemiAnnualFood","inspectScore":100,"inspectDate":"02/01/2017"},{"restId":"34006268","inspectId":"54007239","inspectType":"SemiAnnualFood","inspectScore":100,"inspectDate":"08/22/2016"}],"name": "The One Horse Tavern","yelpImage": "https://s3-media1.fl.yelpcdn.com/bphoto/YAgJHCcYKqF1Qh80jpYWfQ/o.jpg","yelpReviews": "24","yelpRating": "4.5","yelpPrice": "$$","yelpLink": "https://www.yelp.com/biz/the-one-horse-tavern-gaston?adjust_creative=y3SahuoXaK0Or0x6r1lgVw&utm_campaign=yelp_api_v3&utm_medium=api_v3_business_search&utm_source=y3SahuoXaK0Or0x6r1lgVw","cuisines": ["Bars","Burgers","American (Traditional)"]}},{"type": "Feature","geometry": {"type": "Point","coordinates": [-123.13911,45.43755]},"properties": {"inspections": [{"restId":"34009582","inspectId":"54007557","inspectType":"MobileSemi","inspectScore":"Not scored","inspectDate":"03/30/2017"},{"restId":"34009582","inspectId":"54007357","inspectType":"MobileSemi","inspectScore":"Not scored","inspectDate":"10/28/2016"}],"name": "Scoggins Creek Coffee","yelpImage": "https://s3-media1.fl.yelpcdn.com/bphoto/1ECGWp1ivAXC0ZJ7LlUQnA/o.jpg","yelpReviews": "4","yelpRating": "4.5","yelpPrice": "$","yelpLink": "https://www.yelp.com/biz/scoggins-creek-coffee-gaston?adjust_creative=y3SahuoXaK0Or0x6r1lgVw&utm_campaign=yelp_api_v3&utm_medium=api_v3_business_search&utm_source=y3SahuoXaK0Or0x6r1lgVw","cuisines": ["Coffee & Tea"]}},{"type": "Feature","geometry": {"type": "Point","coordinates": [-123.139761,45.4359217]},"properties": {"inspections": [{"restId":"34009851","inspectId":"54007555","inspectType":"ReinspectFood","inspectScore":"Not scored","inspectDate":"03/30/2017"},{"restId":"34009851","inspectId":"54007538","inspectType":"SemiAnnualFood","inspectScore":85,"inspectDate":"03/15/2017"},{"restId":"34009851","inspectId":"54007271","inspectType":"ReinspectFood","inspectScore":"Not scored","inspectDate":"09/06/2016"},{"restId":"34009851","inspectId":"54007240","inspectType":"SemiAnnualFood","inspectScore":87,"inspectDate":"08/22/2016"}],"name": "Screamin' Chicken Diner","yelpImage": "https://s3-media2.fl.yelpcdn.com/bphoto/Tbmv5IOIXlQY5HBROLwxMA/o.jpg","yelpReviews": "40","yelpRating": "4","yelpPrice": "$","yelpLink": "https://www.yelp.com/biz/screamin-chicken-diner-gaston?adjust_creative=y3SahuoXaK0Or0x6r1lgVw&utm_campaign=yelp_api_v3&utm_medium=api_v3_business_search&utm_source=y3SahuoXaK0Or0x6r1lgVw","cuisines": ["Diners","American (Traditional)"]}}]}